odoo/addons/hr_holidays_validity_date/README.rst
odoo/addons/hr_holidays_validity_date/__init__.py
odoo/addons/hr_holidays_validity_date/__manifest__.py
odoo/addons/hr_holidays_validity_date/i18n/ar.po
odoo/addons/hr_holidays_validity_date/i18n/cs_CZ.po
odoo/addons/hr_holidays_validity_date/i18n/de.po
odoo/addons/hr_holidays_validity_date/i18n/es.po
odoo/addons/hr_holidays_validity_date/i18n/fr.po
odoo/addons/hr_holidays_validity_date/i18n/hr.po
odoo/addons/hr_holidays_validity_date/i18n/hr_HR.po
odoo/addons/hr_holidays_validity_date/i18n/hr_holidays_validity_date.pot
odoo/addons/hr_holidays_validity_date/i18n/sl.po
odoo/addons/hr_holidays_validity_date/migrations/12.0.2.0.0/pre-migration.py
odoo/addons/hr_holidays_validity_date/models/__init__.py
odoo/addons/hr_holidays_validity_date/models/hr_leave.py
odoo/addons/hr_holidays_validity_date/models/hr_leave_allocation.py
odoo/addons/hr_holidays_validity_date/readme/CONTRIBUTORS.rst
odoo/addons/hr_holidays_validity_date/readme/DESCRIPTION.rst
odoo/addons/hr_holidays_validity_date/readme/HISTORY.rst
odoo/addons/hr_holidays_validity_date/static/description/icon.png
odoo/addons/hr_holidays_validity_date/static/description/index.html
odoo/addons/hr_holidays_validity_date/tests/__init__.py
odoo/addons/hr_holidays_validity_date/tests/test_hr_holidays_validity_date.py
odoo/addons/hr_holidays_validity_date/views/hr_holidays_view.xml
odoo12_addon_hr_holidays_validity_date-12.0.1.1.0.dist-info/METADATA
odoo12_addon_hr_holidays_validity_date-12.0.1.1.0.dist-info/WHEEL
odoo12_addon_hr_holidays_validity_date-12.0.1.1.0.dist-info/top_level.txt
odoo12_addon_hr_holidays_validity_date-12.0.1.1.0.dist-info/RECORD
